yosemite_tiny/__init__.py
yosemite_tiny/main.py
yosemite_tiny/__cli__/__init__.py
yosemite_tiny/__cli__/cli.py
yosemite_tiny/tools/__init__.py
yosemite_tiny/tools/cli.py
yosemite_tiny/tools/input.py
yosemite_tiny/tools/lightspeed.py
yosemite_tiny/tools/load.py
yosemite_tiny/tools/text.py
yosemite_tiny-0.1.2.dist-info/METADATA
yosemite_tiny-0.1.2.dist-info/WHEEL
yosemite_tiny-0.1.2.dist-info/entry_points.txt
yosemite_tiny-0.1.2.dist-info/top_level.txt
yosemite_tiny-0.1.2.dist-info/RECORD
