Metadata-Version: 2.1
Name: yosemite-tiny
Version: 0.1.2
Summary: yosemite tiny
Author: Hammad Saeed
Author-email: hammad@supportvectors.com
Classifier: Programming Language :: Python :: 3
Classifier: License :: OSI Approved :: MIT License
Classifier: Operating System :: OS Independent
Requires-Python: >3.9
Requires-Dist: art
Requires-Dist: libhammadpy-text
Requires-Dist: prompt-toolkit
Requires-Dist: wcwidth
